[
    {
        "species": "Pachirisu",
        "level": 17,
        "nature": "Sassy",
        "ability": "Pickup",
        "moves": [
            "Charm",
            "Quick Attack",
            "Spark",
            "Endure"
        ],
        "ivs": {
            "hp": 0,
            "atk": 0,
            "def": 0,
            "spa": 0,
            "spd": 0,
            "spe": 0
        },
        "evs": {
            "hp": 0,
            "atk": 0,
            "def": 0,
            "spa": 0,
            "spd": 0,
            "spe": 0
        }
    }
]