[
    {
        "species": "Golbat",
        "level": 35,
        "nature": "Sassy",
        "ability": "Inner Focus",
        "moves": [
            "Mean Look",
            "Poison Fang",
            "Air Cutter",
            "Bite"
        ],
        "ivs": {
            "hp": 0,
            "atk": 0,
            "def": 0,
            "spa": 0,
            "spd": 0,
            "spe": 0
        },
        "evs": {
            "hp": 0,
            "atk": 0,
            "def": 0,
            "spa": 0,
            "spd": 0,
            "spe": 0
        }
    },
    {
        "species": "Graveler",
        "level": 35,
        "nature": "Relaxed",
        "ability": "Rock Head",
        "moves": [
            "Sandstorm",
            "Harden",
            "Smack Down",
            "Bulldoze"
        ],
        "ivs": {
            "hp": 0,
            "atk": 0,
            "def": 0,
            "spa": 0,
            "spd": 0,
            "spe": 0
        },
        "evs": {
            "hp": 0,
            "atk": 0,
            "def": 0,
            "spa": 0,
            "spd": 0,
            "spe": 0
        }
    },
    {
        "species": "Onix",
        "level": 35,
        "nature": "Relaxed",
        "ability": "Sturdy",
        "moves": [
            "Smack Down",
            "Curse",
            "Screech",
            "Sand Tomb"
        ],
        "ivs": {
            "hp": 0,
            "atk": 0,
            "def": 0,
            "spa": 0,
            "spd": 0,
            "spe": 0
        },
        "evs": {
            "hp": 0,
            "atk": 0,
            "def": 0,
            "spa": 0,
            "spd": 0,
            "spe": 0
        }
    }
]