[
    {
        "name": "",
        "species": "Granbull",
        "item": "",
        "ability": "",
        "gender": "",
        "nature": "Hardy",
        "evs": {
            "hp": 0,
            "atk": 0,
            "def": 0,
            "spa": 0,
            "spd": 0,
            "spe": 0
        },
        "ivs": {
            "hp": 31,
            "atk": 31,
            "def": 31,
            "spa": 31,
            "spd": 31,
            "spe": 31
        },
        "level": -3,
        "moves": [
            "Play Rough",
            "Headbutt",
            "Fire Fang",
            "Bite"
        ]
    },
    {
        "name": "",
        "species": "Togetic",
        "item": "",
        "ability": "",
        "gender": "",
        "nature": "Hardy",
        "evs": {
            "hp": 0,
            "atk": 0,
            "def": 0,
            "spa": 0,
            "spd": 0,
            "spe": 0
        },
        "ivs": {
            "hp": 31,
            "atk": 31,
            "def": 31,
            "spa": 31,
            "spd": 31,
            "spe": 31
        },
        "level": -3,
        "moves": [
            "Air Cutter",
            "Ancient Power",
            "Soft Boiled",
            "Magical Leaf"
        ]
    },
    {
        "name": "",
        "species": "Furfrou",
        "item": "",
        "ability": "",
        "gender": "",
        "nature": "Hardy",
        "evs": {
            "hp": 0,
            "atk": 0,
            "def": 0,
            "spa": 0,
            "spd": 0,
            "spe": 0
        },
        "ivs": {
            "hp": 31,
            "atk": 31,
            "def": 31,
            "spa": 31,
            "spd": 31,
            "spe": 31
        },
        "level": -3,
        "moves": [
            "Headbutt",
            "Cotton Guard",
            "Charm",
            "Bite"
        ]
    }
]