[
    {
        "species": "Mew",
        "item": "Leftovers",
        "ability": "Synchronize",
        "evs": {
            "hp": 248,
            "spd": 84,
            "spe": 176
        },
        "nature": "Timid",
        "moves": [
            "Psyshock",
            "Soft-Boiled",
            "Taunt",
            "Will-O-Wisp"
        ]
    },
    {
        "species": "Heracross",
        "gender": "F",
        "item": "Leftovers",
        "ability": "Guts",
        "evs": {
            "atk": 252,
            "def": 4,
            "spe": 252
        },
        "nature": "Jolly",
        "moves": [
            "Close Combat",
            "Megahorn",
            "Stone Edge",
            "Swords Dance"
        ]
    },
    {
        "species": "Qwilfish",
        "gender": "F",
        "item": "Black Sludge",
        "ability": "Intimidate",
        "evs": {
            "hp": 248,
            "def": 200,
            "spe": 60
        },
        "nature": "Bold",
        "moves": [
            "Pain Split",
            "Scald",
            "Spikes",
            "Taunt"
        ]
    },
    {
        "species": "Rhyperior",
        "gender": "M",
        "item": "Leftovers",
        "ability": "Solid Rock",
        "evs": {
            "hp": 244,
            "atk": 16,
            "spd": 248
        },
        "nature": "Adamant",
        "moves": [
            "Dragon Tail",
            "Earthquake",
            "Rock Blast",
            "Stealth Rock"
        ]
    },
    {
        "species": "Togekiss",
        "gender": "M",
        "item": "Leftovers",
        "ability": "Serene Grace",
        "evs": {
            "hp": 248,
            "def": 160,
            "spe": 100
        },
        "nature": "Bold",
        "moves": [
            "Air Slash",
            "Heal Bell",
            "Nasty Plot",
            "Roost"
        ]
    },
    {
        "species": "Umbreon",
        "gender": "M",
        "item": "Leftovers",
        "ability": "Synchronize",
        "evs": {
            "hp": 252,
            "spd": 252,
            "spe": 4
        },
        "nature": "Calm",
        "moves": [
            "Foul Play",
            "Protect",
            "Toxic",
            "Wish"
        ]
    }
]