[
    {
        "species": "Gardevoir",
        "gender": "M",
        "item": "Gardevoirite",
        "ability": "Trace",
        "evs": {
            "hp": 184,
            "spa": 140,
            "spe": 184
        },
        "nature": "Modest",
        "ivs": {
            "atk": 0
        },
        "moves": [
            "Calm Mind",
            "Hyper Voice",
            "Protect",
            "Psyshock"
        ]
    },
    {
        "species": "Amoonguss",
        "gender": "M",
        "item": "Rocky Helmet",
        "ability": "Regenerator",
        "evs": {
            "hp": 232,
            "def": 96,
            "spd": 180
        },
        "nature": "Sassy",
        "ivs": {
            "atk": 0
        },
        "moves": [
            "Protect",
            "Rage Powder",
            "Sludge Bomb",
            "Spore"
        ]
    },
    {
        "species": "Landorus-Therian",
        "item": "Assault Vest",
        "ability": "Intimidate",
        "evs": {
            "hp": 248,
            "def": 52,
            "spd": 112,
            "spe": 96
        },
        "nature": "Careful",
        "moves": [
            "Earthquake",
            "Stone Edge",
            "Superpower",
            "U-turn"
        ]
    },
    {
        "species": "Thundurus",
        "item": "Sitrus Berry",
        "ability": "Prankster",
        "evs": {
            "hp": 248,
            "spd": 252,
            "spe": 8
        },
        "nature": "Timid",
        "moves": [
            "Hidden Power Ice",
            "Superpower",
            "Thunderbolt",
            "Thunder Wave"
        ],
        "ivs": {
            "atk": 30,
            "def": 30
        }
    },
    {
        "species": "Togekiss",
        "gender": "M",
        "item": "Safety Goggles",
        "ability": "Serene Grace",
        "evs": {
            "hp": 252,
            "spd": 72,
            "spe": 184
        },
        "nature": "Calm",
        "ivs": {
            "atk": 0
        },
        "moves": [
            "Fire Blast",
            "Follow Me",
            "Protect",
            "Tailwind"
        ]
    },
    {
        "species": "Volcanion",
        "item": "Assault Vest",
        "ability": "Water Absorb",
        "evs": {
            "hp": 252,
            "spd": 184,
            "spe": 72
        },
        "nature": "Modest",
        "ivs": {
            "atk": 0,
            "spa": 30
        },
        "moves": [
            "Earth Power",
            "Heat Wave",
            "Hidden Power Grass",
            "Steam Eruption"
        ]
    }
]