[
    {
        "species": "Kingambit",
        "gender": "F",
        "item": "Leftovers",
        "ability": "Supreme Overlord",
        "teraType": "Dark",
        "evs": {
            "hp": 160,
            "atk": 252,
            "spe": 96
        },
        "nature": "Adamant",
        "moves": [
            "Iron Head",
            "Kowtow Cleave",
            "Sucker Punch",
            "Swords Dance"
        ]
    },
    {
        "species": "Cinderace",
        "gender": "F",
        "item": "Heavy-Duty Boots",
        "ability": "Blaze",
        "shiny": true,
        "teraType": "Flying",
        "evs": {
            "hp": 144,
            "atk": 112,
            "spe": 252
        },
        "nature": "Jolly",
        "moves": [
            "Court Change",
            "Pyro Ball",
            "U-turn",
            "Will-O-Wisp"
        ]
    },
    {
        "species": "Iron Valiant",
        "item": "Booster Energy",
        "ability": "Quark Drive",
        "teraType": "Ghost",
        "evs": {
            "atk": 176,
            "spa": 80,
            "spe": 252
        },
        "nature": "Naive",
        "moves": [
            "Close Combat",
            "Encore",
            "Knock Off",
            "Moonblast"
        ]
    },
    {
        "species": "Kyurem",
        "item": "Choice Specs",
        "ability": "Pressure",
        "shiny": true,
        "teraType": "Ice",
        "evs": {
            "def": 4,
            "spa": 252,
            "spe": 252
        },
        "nature": "Timid",
        "ivs": {
            "atk": 0
        },
        "moves": [
            "Blizzard",
            "Draco Meteor",
            "Earth Power",
            "Freeze-Dry"
        ]
    },
    {
        "species": "Landorus-Therian",
        "item": "Rocky Helmet",
        "ability": "Intimidate",
        "shiny": true,
        "teraType": "Dragon",
        "evs": {
            "hp": 248,
            "def": 244,
            "spe": 16
        },
        "nature": "Bold",
        "moves": [
            "Earth Power",
            "Stealth Rock",
            "Taunt",
            "U-turn"
        ]
    },
    {
        "species": "Slowking-Galar",
        "gender": "M",
        "item": "Heavy-Duty Boots",
        "ability": "Regenerator",
        "shiny": true,
        "teraType": "Water",
        "evs": {
            "hp": 248,
            "def": 8,
            "spd": 252
        },
        "nature": "Sassy",
        "ivs": {
            "atk": 0,
            "spe": 0
        },
        "moves": [
            "Chilly Reception",
            "Future Sight",
            "Surf",
            "Toxic"
        ]
    }
]